{
    "timestamp_utc": "2025-10-07T09:31:32.192518+00:00",
    "market_vector": {
        "price_usd": 124236.1
    },
    "mining_vector": {
        "difficulty_change_percent": -7.665048725403334,
        "next_retarget_blocks": 1277
    },
    "monetary_vector": {
        "circulating_supply": 19931309.375,
        "current_block_reward": 3.125,
        "blocks_until_next_halving": 131981
    },
    "speculative_vector": {
        "open_interest": 0,
        "funding_rate": 0,
        "error": true
    },
    "trend_vector": {
        "rsi_14d": 70.69729704980375,
        "historical_prices": [
            117135.7,
            115677.2,
            115739.1,
            115298.9,
            112747.8,
            112001.5,
            113300.0,
            109049.8,
            109706.3,
            109720.5,
            112127.8,
            114365.2,
            113995.0,
            118599.9,
            120649.9,
            122259.5,
            122426.4,
            123542.1,
            124766.5,
            124218.8
        ],
        "price_change_percent": 0.1190446445626718
    },
    "singularity_score": 54,
    "narrative_vector": {
        "primary": "Market sentiment is overheated (RSI: 71). A correction is probable.",
        "market": "Momentum is neutral (RSI: 70.7). The derivatives market is balanced.",
        "network": "The -7.67% difficulty adjustment indicates the security baseline is holding steady."
    }
}